{"stat.chestOpened":1,"stat.flyOneCm":20632,"stat.deaths":5,"stat.walkOneCm":170249,"stat.jump":283,"stat.swimOneCm":5846,"stat.playOneMinute":32231,"achievement.openInventory":1,"stat.fallOneCm":6920,"stat.leaveGame":6,"stat.damageTaken":1234,"stat.damageDealt":280,"stat.crouchOneCm":546,"stat.timeSinceDeath":5542,"stat.useItem.minecraft.dirt":1,"stat.sprintOneCm":46574,"stat.mineBlock.minecraft.dirt":1,"achievement.exploreAllBiomes":{"value":0,"progress":["Sunflower Plains","Forest","Plains","Savanna"]},"stat.mineBlock.minecraft.tallgrass":4,"stat.diveOneCm":13645,"stat.entityKilledBy.Creeper":1}